jarvismode/__init__.py
jarvismode/__main__.py
jarvismode/alembic.ini
jarvismode/main.py
jarvismode/memory.py
jarvismode/middleware.py
jarvismode/py.typed
jarvismode/server.py
jarvismode/settings.py
jarvismode/worker.py
jarvismode/alembic/README
jarvismode/alembic/env.py
jarvismode/alembic/script.py.mako
jarvismode/alembic/versions/006b3990db50_add_unique_constraints.py
jarvismode/alembic/versions/012fb73ac359_add_folder_table.py
jarvismode/alembic/versions/0ae3a2674f32_update_the_columns_that_need_to_change_.py
jarvismode/alembic/versions/0b8757876a7c_.py
jarvismode/alembic/versions/0d60fcbd4e8e_create_vertex_builds_table.py
jarvismode/alembic/versions/1a110b568907_replace_credential_table_with_variable.py
jarvismode/alembic/versions/1c79524817ed_add_unique_constraints_per_user_in_.py
jarvismode/alembic/versions/1d90f8a0efe1_update_description_columns_type.py
jarvismode/alembic/versions/1eab2c3eb45e_event_error.py
jarvismode/alembic/versions/1ef9c4f3765d_.py
jarvismode/alembic/versions/1f4d6df60295_add_default_fields_column.py
jarvismode/alembic/versions/260dbcc8b680_adds_tables.py
jarvismode/alembic/versions/29fe8f1f806b_add_missing_index.py
jarvismode/alembic/versions/2ac71eb9c3ae_adds_credential_table.py
jarvismode/alembic/versions/3bb0ddf32dfb_add_unique_constraints_per_user_in_flow_.py
jarvismode/alembic/versions/4e5980a44eaa_fix_date_times_again.py
jarvismode/alembic/versions/58b28437a398_modify_nullable.py
jarvismode/alembic/versions/5ace73a7f223_new_remove_table_upgrade_op.py
jarvismode/alembic/versions/631faacf5da2_add_webhook_columns.py
jarvismode/alembic/versions/63b9c451fd30_add_icon_and_icon_bg_color_to_flow.py
jarvismode/alembic/versions/67cc006d50bf_add_profile_image_column.py
jarvismode/alembic/versions/6e7b581b5648_fix_nullable.py
jarvismode/alembic/versions/7843803a87b5_store_updates.py
jarvismode/alembic/versions/79e675cb6752_change_datetime_type.py
jarvismode/alembic/versions/7d2162acc8b2_adds_updated_at_and_folder_cols.py
jarvismode_base-1.0.14.dist-info/METADATA
jarvismode_base-1.0.14.dist-info/WHEEL
jarvismode_base-1.0.14.dist-info/entry_points.txt
jarvismode_base-1.0.14.dist-info/RECORD
